scheduler/__init__.py
scheduler/__main__.py
scheduler/input_command.py
scheduler/main.py
scheduler/make_string.py
scheduler/valid_date.py
scheduler_todo-1.0.2.dist-info/DESCRIPTION.rst
scheduler_todo-1.0.2.dist-info/METADATA
scheduler_todo-1.0.2.dist-info/RECORD
scheduler_todo-1.0.2.dist-info/WHEEL
scheduler_todo-1.0.2.dist-info/entry_points.txt
scheduler_todo-1.0.2.dist-info/metadata.json
scheduler_todo-1.0.2.dist-info/top_level.txt
server/__init__.py
server/__main__.py
server/main.py
slackbot/__init__.py
slackbot/__main__.py
slackbot/input_command.py
slackbot/main.py
slackbot/make_string.py
slackbot/valid_date.py
