Metadata-Version: 2.0
Name: scheduler-todo
Version: 1.0.2
Summary: A scheduler command line program in Python.
Home-page: https://github.com/jil8885/scheduler-cli
Author: Jeongin Lee
Author-email: jil8885@hanynag.ac.kr
License: MIT LICENSE
Keywords: cli,scheduler-cli
Platform: UNKNOWN
Classifier: Programming Language :: Python :: 3.4
Classifier: Programming Language :: Python :: 3.5
Classifier: Programming Language :: Python :: 3.6
Requires-Dist: colorama
Requires-Dist: flask
Requires-Dist: requests
Requires-Dist: slacker
Requires-Dist: termcolor
Requires-Dist: websocket-client
